{"courseType":"v2.ondemand","description":"Les participants intéressés par Google Cloud Platform peuvent continuer leur apprentissage en suivant l'une de nos nouvelles spécialisations consacrées à l'infrastructure de GCP.\n\nOption 1 : La spécialisation Developing Applications with Google Cloud Platform est disponible depuis peu sur Coursera. Vous y apprendrez à créer des applications cloud natives sécurisées, évolutives et intelligentes. Rendez-vous sur https://www.coursera.org/specializations/developing-apps-gcp pour en savoir plus.\n\nOption 2 : La spécialisation Architecting with Google Cloud Platform est également disponible. Son contenu a été mis à jour et amélioré. Cette spécialisation vous aidera à préparer l'examen Google Certified Professional – Cloud Architect. Accédez à https://www.coursera.org/specializations/gcp-architecture pour explorer le contenu mis à jour.\n\nLe cours Google Cloud Platform Fundamentals: Core Infrastructure couvre les bases de Google Cloud Platform et constitue le premier cours de ces deux spécialisations. \n\nIl présente des concepts et termes importants de Google Cloud Platform (GCP). Vous y découvrirez et pourrez comparer de nombreux services de calcul et de stockage disponibles dans Google Cloud Platform, dont Google App Engine, Google Compute Engine et Google Container Engine.\n\nRemarques :\n• Vous avez besoin d'un compte Google/Gmail, et d'une carte de crédit ou d'un compte bancaire pour vous inscrire à l'essai gratuit de Google Cloud Platform. (Les services Google sont actuellement indisponibles en Chine.)\n• Si votre adresse de facturation pour les services GCP est située en Union européenne (UE) ou en Russie, lisez la documentation relative à la TVA à l'adresse suivante : https://cloud.google.com/billing/docs/resources/vat-overview.\n• Vous trouverez d'autres questions fréquentes relatives à l'essai gratuit de GCP à l'adresse suivante : https://cloud.google.com/free/?hl=fr.","id":"Tq_sjE-_EeiNBQqYqBGpZg","slug":"gcp-fundamentals-fr","instructorIds":["22997770"],"specializations":[],"partnerIds":["443"],"name":"Google Cloud Platform Fundamentals: Core Infrastructure en Français"}