{"courseType":"v2.ondemand","description":"Businesses and their supply chains are facing increasing competition and uncertainty in what is now a truly globalised trade environment. To remain competitive, organisations need to think globally – ensuring supply chains meet customer demands while minimising costs and maximising responsiveness. From a strategic perspective, this involves making important trade-off decisions between cost, quality and flexibility of supply chains. Via structured learning activities (video lectures, quizzes, discussion prompts and written assessments) this course will equip you with the future-focused capabilities needed to design and manage effective, sustainable and efficient global supply chains of tomorrow.","id":"Cryjy28DEeis-grgLlL-jg","slug":"supply-chain-management-global","instructorIds":["33668383"],"specializations":[],"partnerIds":["254"],"name":"Supply chain management: Be global"}