{"courseType":"v2.ondemand","description":"Much of the world's data resides in databases. SQL (or Structured Query Language) is a powerful language which is used for communicating with and extracting data from databases. A working knowledge of databases and SQL is a must if you want to become a data scientist.\n\nThe purpose of this course is to introduce relational database concepts and help you learn and apply foundational knowledge of the SQL language. It is also intended to get you started with performing SQL access in a data science environment.  \n\nThe emphasis in this course is on hands-on and practical learning . As such, you will work with real databases, real data science tools, and real-world datasets. You will create a database instance in the cloud. Through a series of hands-on labs you will practice building and running SQL queries. You will also learn how to access databases from Jupyter notebooks using SQL and Python.\n\nNo prior knowledge of databases, SQL, Python, or programming is required.\n\nAnyone can audit this course at no-charge. If you choose to take this course and earn the Coursera course certificate, you can also earn an IBM digital badge upon successful completion of the course.\n\nLIMITED TIME OFFER: Subscription is only $39 USD per month for access to graded materials and a certificate.","id":"GDQMSxDWEeitFhJL4G-A_g","slug":"sql-data-science","instructorIds":["28513748"],"specializations":[],"partnerIds":["348"],"name":"Databases and SQL for Data Science"}